[
  {
    "id": "f1",
    "title": "World's Highest Cricket Ground",
    "text": "India's Chail Cricket Ground in Himachal Pradesh sits at 2,444 meters above sea level — one of the highest in the world.",
    "category": "Nature & Places",
    "image": "https://picsum.photos/seed/chail/1200/600"
  },
  {
    "id": "f2",
    "title": "Jagadish Chandra Bose and Plant Responses",
    "text": "Sir Jagadish Chandra Bose pioneered work on plant responses and was among the first Indians to achieve international recognition in radio and biology.",
    "category": "Science & Innovation",
    "image": "https://picsum.photos/seed/bose/1200/600"
  },
  {
    "id": "f3",
    "title": "Largest Postal Network",
    "text": "India has one of the world's largest postal networks with over 150,000 post offices serving remote regions.",
    "category": "Society",
    "image": "https://picsum.photos/seed/post/1200/600"
  }
]
